examples/binary_search/app.py
examples/binary_search/app/__init__.py
examples/binary_search/app/__main__.py
examples/binary_search/app/app.py
examples/binary_search/app/controllers/__init__.py
examples/binary_search/app/controllers/base_controller.py
examples/binary_search/app/controllers/binary_search.py
examples/binary_search/app/decorators/__init__.py
examples/binary_search/app/decorators/decorators_random.py
examples/binary_search/app/helpers/__init__.py
examples/binary_search/app/interfaces/__init__.py
examples/binary_search/app/interfaces/base_controller.py
examples/binary_search/app/interfaces/base_model.py
examples/binary_search/app/interfaces/base_view.py
examples/binary_search/app/models/__init__.py
examples/binary_search/app/models/base_model.py
examples/binary_search/app/models/binary_search.py
examples/binary_search/app/models/random_data.py
examples/binary_search/app/models/entities/__init__.py
examples/binary_search/app/views/__init__.py
examples/binary_search/app/views/base_view.py
examples/binary_search/app/views/binary_search.py
examples/binary_search/tests/__init__.py
examples/binary_search/tests/test_default.py
examples/codebreaker/app.py
examples/codebreaker/app/__init__.py
examples/codebreaker/app/__main__.py
examples/codebreaker/app/app.py
examples/codebreaker/app/controllers/__init__.py
examples/codebreaker/app/controllers/base_controller.py
examples/codebreaker/app/controllers/codebreaker_easy.py
examples/codebreaker/app/controllers/codebreaker_hard.py
examples/codebreaker/app/controllers/codebreaker_normal.py
examples/codebreaker/app/decorators/__init__.py
examples/codebreaker/app/helpers/__init__.py
examples/codebreaker/app/interfaces/__init__.py
examples/codebreaker/app/interfaces/base_controller.py
examples/codebreaker/app/interfaces/base_model.py
examples/codebreaker/app/interfaces/base_view.py
examples/codebreaker/app/models/__init__.py
examples/codebreaker/app/models/base_model.py
examples/codebreaker/app/models/codebreaker.py
pmvcs-1.0.4.dist-info/LICENSE
pmvcs-1.0.4.dist-info/METADATA
pmvcs-1.0.4.dist-info/PKG-INFO (1)
pmvcs-1.0.4.dist-info/SOURCES (1).txt
pmvcs-1.0.4.dist-info/WHEEL
pmvcs-1.0.4.dist-info/entry_points.txt
pmvcs-1.0.4.dist-info/top_level.txt
pmvcs-1.0.4.dist-info/RECORD
