Metadata-Version: 2.1
Name: pmvcs
Version: 1.0.4
Summary: Python MVC Shell Framework Package is a tiny framework for shell projects in Python.
Author-email: Gonzalo Mahserdjian <gsmx64@outlook.com>
License: GNU/GPL version 3
Project-URL: Homepage, https://github.com/gsmx64/pmvcs
Project-URL: Bug Tracker, https://github.com/gsmx64/pmvcs/issues
Keywords: pmvcs,python shell,python mvc,python shell framework,python mvc,python mvc shell framework
Classifier: Programming Language :: Python :: 3
Classifier: License :: OSI Approved :: GNU General Public License v3 (GPLv3)
Classifier: Operating System :: OS Independent
Requires-Python: >=3.7
License-File: LICENSE
